{
  "_class": "shapeGroup",
  "clippingMaskMode": 0,
  "do_objectID": "BCA6329C-9702-45A6-BAAE-7EAC0E01CF6E",
  "exportOptions": {
    "_class": "exportOptions",
    "exportFormats": [
    ],
    "includedLayerIds": [
    ],
    "layerOptions": 0,
    "shouldTrim": false
  },
  "frame": {
    "_class": "rect",
    "constrainProportions": false,
    "height": 25,
    "width": 115,
    "x": 0,
    "y": 0
  },
  "hasClickThrough": false,
  "hasClippingMask": false,
  "isFlippedHorizontal": false,
  "isFlippedVertical": false,
  "isLocked": false,
  "isVisible": true,
  "layerListExpandedType": 1,
  "layers": [
    {
      "class": "rectangle",
      "id": "4DD89FE0-DFBA-4FB9-A26B-1AF76E76DDE8"
    }
  ],
  "name": "Input field",
  "nameIsFixed": true,
  "resizingConstraint": 63,
  "resizingType": 0,
  "rotation": 0,
  "shouldBreakMaskChain": false,
  "style": {
    "_class": "style",
    "endDecorationType": 0,
    "fills": [
      {
        "_class": "fill",
        "color": {
          "_class": "color",
          "alpha": 1,
          "blue": 1,
          "green": 1,
          "red": 1
        },
        "do_objectID": "D11828BC-0808-4454-A3F1-905562343F25",
        "fillType": 0,
        "isEnabled": true,
        "noiseIndex": 0,
        "noiseIntensity": 0,
        "patternFillType": 0,
        "patternTileScale": 1
      }
    ],
    "miterLimit": 10,
    "shadows": [
      {
        "_class": "shadow",
        "blurRadius": 0,
        "color": {
          "_class": "color",
          "alpha": 1,
          "blue": 0.8980392156862745,
          "green": 0.8980392156862745,
          "red": 0.8980392156862745
        },
        "contextSettings": {
          "_class": "graphicsContextSettings",
          "blendMode": 0,
          "opacity": 1
        },
        "do_objectID": "666C908C-F666-49B8-8D3A-DEEE4CA50AF3",
        "isEnabled": true,
        "offsetX": 0,
        "offsetY": 2,
        "spread": 0
      }
    ],
    "startDecorationType": 0
  },
  "windingRule": 1
}