{
  "_class": "group",
  "do_objectID": "101DDBDD-1126-4DAA-87CC-DBA37D36C2BB",
  "exportOptions": {
    "_class": "exportOptions",
    "do_objectID": "0D2C6C5C-D859-4440-A301-EE8FBE8EB9D1",
    "exportFormats": [
    ],
    "includedLayerIds": [
    ],
    "layerOptions": 0,
    "shouldTrim": false
  },
  "frame": {
    "_class": "rect",
    "constrainProportions": false,
    "do_objectID": "6593B3F9-59BA-4C0D-A749-E17572A42C77",
    "height": 203,
    "width": 640,
    "x": 306,
    "y": 197
  },
  "hasClickThrough": false,
  "isFlippedHorizontal": false,
  "isFlippedVertical": false,
  "isLocked": false,
  "isVisible": true,
  "layerListExpandedType": 0,
  "layers": [
    {
      "class": "group",
      "id": "F1A8914C-91B0-4829-B068-BB427879E69F"
    },
    {
      "class": "group",
      "id": "B9054ABE-D5F7-4E37-8472-49EFA50E8A39"
    },
    {
      "class": "group",
      "id": "7513C818-4CFD-4CD7-8D09-C3D106289A98"
    }
  ],
  "name": "FAQ",
  "nameIsFixed": true,
  "resizingConstraint": 63,
  "resizingType": 0,
  "rotation": 0,
  "shouldBreakMaskChain": false,
  "style": {
    "_class": "style",
    "do_objectID": "D1A2905D-0EFF-441A-AB91-844F348CDCC6",
    "endDecorationType": 0,
    "miterLimit": 10,
    "startDecorationType": 0
  }
}