{
  "_class": "group",
  "do_objectID": "B7C79143-6409-4C5A-832B-0DD0D55118F4",
  "exportOptions": {
    "_class": "exportOptions",
    "do_objectID": "D37D176F-3F81-4F2C-A76D-F950D65C6DA9",
    "exportFormats": [
    ],
    "includedLayerIds": [
    ],
    "layerOptions": 0,
    "shouldTrim": false
  },
  "frame": {
    "_class": "rect",
    "constrainProportions": false,
    "do_objectID": "391E26CC-931F-411A-A7D2-8FCD46E32A1A",
    "height": 96,
    "width": 489,
    "x": 0,
    "y": 221
  },
  "hasClickThrough": false,
  "isFlippedHorizontal": false,
  "isFlippedVertical": false,
  "isLocked": false,
  "isVisible": true,
  "layerListExpandedType": 0,
  "layers": [
    {
      "class": "text",
      "id": "1D014286-1E3A-4A6D-81E6-E6CDD60561B5"
    },
    {
      "class": "text",
      "id": "C28C04DB-403D-4132-BB9F-21F01F62A174"
    },
    {
      "class": "text",
      "id": "594B7DF5-ABE5-477C-AC34-A2EFEA6843D8"
    },
    {
      "class": "shapeGroup",
      "id": "D281897E-76AE-42C2-9505-EA541AD686F8"
    }
  ],
  "name": "2",
  "nameIsFixed": true,
  "resizingConstraint": 63,
  "resizingType": 0,
  "rotation": 0,
  "shouldBreakMaskChain": false,
  "style": {
    "_class": "style",
    "do_objectID": "DD5760FA-1DC6-461B-A1B9-FC1463607568",
    "endDecorationType": 0,
    "miterLimit": 10,
    "startDecorationType": 0
  }
}